<?xml version="1.0" encoding="UTF-8"?>
<omexManifest xmlns="http://identifiers.org/combine.specifications/omex-manifest">
  <content location="Fig 8.png" format="http://purl.org/NET/mediatypes/image/png" master="false"/>
  <content location="Jung2019 model-biopax2.owl" format="http://purl.org/NET/mediatypes/application/rdf+xml" master="false"/>
  <content location="Jung2019 model-biopax3.owl" format="http://purl.org/NET/mediatypes/application/rdf+xml" master="false"/>
  <content location="Jung2019 model-matlab.m" format="http://purl.org/NET/mediatypes/text/x-matlab" master="false"/>
  <content location="Jung2019 model-octave.m" format="http://purl.org/NET/mediatypes/text/x-matlab" master="false"/>
  <content location="Jung2019 model.xml" format="http://identifiers.org/combine.specifications/sbml" master="false"/>
  <content location="Jung2019 model_urn.xml" format="http://identifiers.org/combine.specifications/sbml" master="false"/>
  <content location="Jung2019 simulation.sedml" format="http://identifiers.org/combine.specifications/sed-ml" master="true"/>
  <content location="Jung2019.cps" format="http://purl.org/NET/mediatypes/application/x-copasi" master="false"/>
</omexManifest>
