<?xml version="1.0" encoding="UTF-8"?>
<sbml xmlns="http://www.sbml.org/sbml/level2/version4" metaid="_324346" level="2" version="4">
  <model metaid="metaid_0000002" id="Phillips2007_AscendingArousalSystem_SleepWakeDynamics" name="Phillips2007_AscendingArousalSystem_SleepWakeDynamics">
    <notes>
      <body xmlns="http://www.w3.org/1999/xhtml">
        <p>This a model from the article:      <br/>
        <strong>A quantitative model of sleep-wake dynamics based on the physiology of the
brainstem ascending arousal system.</strong>
        <br/>
          Phillips AJ, Robinson PA.      <em>J Biol Rhythms</em>
          2007 Apr;22(2):167-79      <a href="http://www.ncbi.nlm.nih.gov/pubmed/17440218">17440218</a>
          ,      <br/>
        <strong>Abstract:</strong>
        <br/>
          A quantitative, physiology-based model of the ascending arousal system is
developed, using continuum neuronal population modeling, which involves
averaging properties such as firing rates across neurons in each population. The
model includes the ventrolateral preoptic area (VLPO), where circadian and
homeostatic drives enter the system, the monoaminergic and cholinergic nuclei of
the ascending arousal system, and their interconnections. The human sleep-wake
cycle is governed by the activities of these nuclei, which modulate the
behavioral state of the brain via diffuse neuromodulatory projections. The model
parameters are not free since they correspond to physiological observables.
Approximate parameter bounds are obtained by requiring consistency with
physiological and behavioral measures, and the model replicates the human
sleep-wake cycle, with physiologically reasonable voltages and firing rates.
Mutual inhibition between the wake-promoting monoaminergic group and
sleep-promoting VLPO causes ;;flip-flop'' behavior, with most time spent in 2
stable steady states corresponding to wake and sleep, with transitions between
them on a timescale of a few minutes. The model predicts hysteresis in the
sleep-wake cycle, with a region of bistability of the wake and sleep states.
Reducing the monoaminergic-VLPO mutual inhibition results in a smaller
hysteresis loop. This makes the model more prone to wake-sleep transitions in
both directions and makes the states less distinguishable, as in narcolepsy. The
model behavior is robust across the constrained parameter ranges, but with
sufficient flexibility to describe a wide range of observed phenomena.      </p>
      <p>This model was taken from the      <a href="http://www.cellml.org/models">CellML repository</a>
          and automatically converted to SBML.      <br/>
          The original model was:      <a href="http://models.cellml.org/exposure/538f7b53af627b47e9d3f66aef27f9e5">
        <strong>Phillips AJ, Robinson PA. (2007) - version=1.0</strong>
      </a>
      <br/>
          The original CellML model was created by:      <br/>
      <strong>Catherine Lloyd</strong>
      <br/>
          c.lloyd@auckland.ac.nz      <br/>
          The University of Auckland      <br/></p>
    <p>This model originates from BioModels Database: A Database of Annotated Published Models (http://www.ebi.ac.uk/biomodels/). It is copyright (c) 2005-2011 The BioModels.net Team.      <br/>
          To the extent possible under law, all copyright and related or neighbouring rights to this encoded model have been dedicated to the public domain worldwide. Please refer to      <a href="http://creativecommons.org/publicdomain/zero/1.0/" title="Creative Commons CC0">CC0 Public Domain Dedication</a>
          for more information.      </p>
  <p>In summary, you are entitled to use this encoded model in absolutely any manner you deem suitable, verbatim, or with modification, alone or embedded it in a larger context, redistribute it, commercially or not, in a restricted way or not..      <br/>
  <br/>
          To cite BioModels Database, please use:      <a href="http://www.ncbi.nlm.nih.gov/pubmed/20587024" target="_blank">Li C, Donizelli M, Rodriguez N, Dharuri H, Endler L, Chelliah V, Li L, He E, Henry A, Stefan MI, Snoep JL, Hucka M, Le Novère N, Laibe C (2010) BioModels Database: An enhanced, curated and annotated resource for published quantitative kinetic models. BMC Syst Biol., 4:92.</a>
</p>
</body>
</notes><annotation>
  <rdf:RDF xmlns:rdf="http://www.w3.org/1999/02/22-rdf-syntax-ns#" xmlns:bqmodel="http://biomodels.net/model-qualifiers/" xmlns:vCard="http://www.w3.org/2001/vcard-rdf/3.0#" xmlns:dc="http://purl.org/dc/elements/1.1/" xmlns:dcterms="http://purl.org/dc/terms/" xmlns:bqbiol="http://biomodels.net/biology-qualifiers/">
    <rdf:Description rdf:about="#metaid_0000002">
      <dc:creator>
        <rdf:Bag>
          <rdf:li rdf:parseType="Resource">
            <vCard:N rdf:parseType="Resource">
              <vCard:Family>Lloyd</vCard:Family>
              <vCard:Given>Catherine</vCard:Given>
            </vCard:N>
            <vCard:EMAIL>c.lloyd@auckland.ac.nz</vCard:EMAIL>
            <vCard:ORG rdf:parseType="Resource">
              <vCard:Orgname>University of Auckland</vCard:Orgname>
            </vCard:ORG>
          </rdf:li>
          <rdf:li rdf:parseType="Resource">
            <vCard:N rdf:parseType="Resource">
              <vCard:Family>Lloyd</vCard:Family>
              <vCard:Given>Catherine</vCard:Given>
            </vCard:N>
            <vCard:EMAIL>c.lloyd@auckland.ac.nz</vCard:EMAIL>
            <vCard:ORG rdf:parseType="Resource">
              <vCard:Orgname>University of Auckland</vCard:Orgname>
            </vCard:ORG>
          </rdf:li>
          <rdf:li rdf:parseType="Resource">
            <vCard:N rdf:parseType="Resource">
              <vCard:Family>Lloyd</vCard:Family>
              <vCard:Given>Catherine</vCard:Given>
            </vCard:N>
            <vCard:EMAIL>c.lloyd@auckland.ac.nz</vCard:EMAIL>
            <vCard:ORG rdf:parseType="Resource">
              <vCard:Orgname>University of Auckland</vCard:Orgname>
            </vCard:ORG>
          </rdf:li>
        </rdf:Bag>
      </dc:creator>
      <dcterms:created rdf:parseType="Resource">
        <dcterms:W3CDTF>2010-06-25T12:34:19Z</dcterms:W3CDTF>
      </dcterms:created>
      <dcterms:modified rdf:parseType="Resource">
        <dcterms:W3CDTF>2010-06-25T12:34:19Z</dcterms:W3CDTF>
      </dcterms:modified>
      <dcterms:modified rdf:parseType="Resource">
        <dcterms:W3CDTF>2010-06-25T12:34:19Z</dcterms:W3CDTF>
      </dcterms:modified>
      <dcterms:modified rdf:parseType="Resource">
        <dcterms:W3CDTF>2010-06-25T12:34:19Z</dcterms:W3CDTF>
      </dcterms:modified>
      <bqmodel:is>
        <rdf:Bag>
          <rdf:li rdf:resource="http://identifiers.org/biomodels.db/MODEL1006230025"/>
        </rdf:Bag>
      </bqmodel:is>
      <bqmodel:isDescribedBy>
        <rdf:Bag>
          <rdf:li rdf:resource="http://identifiers.org/pubmed/17440218"/>
        </rdf:Bag>
      </bqmodel:isDescribedBy>
      <bqbiol:hasTaxon>
        <rdf:Bag>
          <rdf:li rdf:resource="http://identifiers.org/taxonomy/9606"/>
        </rdf:Bag>
      </bqbiol:hasTaxon>
      <bqbiol:isVersionOf>
        <rdf:Bag>
          <rdf:li rdf:resource="http://identifiers.org/go/GO:0022410"/>
        </rdf:Bag>
      </bqbiol:isVersionOf>
      <bqbiol:occursIn>
        <rdf:Bag>
          <rdf:li rdf:resource="http://identifiers.org/bto/BTO:0000146"/>
        </rdf:Bag>
      </bqbiol:occursIn>
    </rdf:Description>
  </rdf:RDF>
</annotation><listOfUnitDefinitions>
  <unitDefinition metaid="_324358" id="mV" name="mV">
    <listOfUnits>
      <unit metaid="_324370" kind="volt" scale="-3"/>
    </listOfUnits>
  </unitDefinition>
  <unitDefinition metaid="_324382" id="mV_second" name="mV_second">
    <listOfUnits>
      <unit metaid="_324394" kind="volt" scale="-3"/>
      <unit metaid="_324406" kind="second"/>
    </listOfUnits>
  </unitDefinition>
  <unitDefinition metaid="_324418" id="hour" name="hour">
    <listOfUnits>
      <unit metaid="_324430" kind="second" multiplier="3600"/>
    </listOfUnits>
  </unitDefinition>
  <unitDefinition metaid="_324442" id="per_hour" name="per_hour">
    <listOfUnits>
      <unit metaid="_324454" kind="second" exponent="-1" multiplier="3600"/>
    </listOfUnits>
  </unitDefinition>
  <unitDefinition metaid="_324466" id="nM" name="nM">
    <listOfUnits>
      <unit metaid="_324479" kind="mole" scale="-9"/>
      <unit metaid="_324491" kind="litre" exponent="-1"/>
    </listOfUnits>
  </unitDefinition>
  <unitDefinition metaid="_324503" id="nM_second" name="nM_second">
    <listOfUnits>
      <unit metaid="_324515" kind="mole" scale="-9"/>
      <unit metaid="_324527" kind="litre" exponent="-1"/>
      <unit metaid="_324539" kind="second"/>
    </listOfUnits>
  </unitDefinition>
  <unitDefinition metaid="_324551" id="mV_per_nM" name="mV_per_nM">
    <listOfUnits>
      <unit metaid="_324563" kind="volt" scale="-3"/>
      <unit metaid="_324575" kind="mole" exponent="-1" scale="-9"/>
      <unit metaid="_324587" kind="litre"/>
    </listOfUnits>
  </unitDefinition>
  <unitDefinition metaid="_324599" id="per_second" name="per_second">
    <listOfUnits>
      <unit metaid="_324611" kind="second" exponent="-1"/>
    </listOfUnits>
  </unitDefinition>
  <unitDefinition metaid="_324623" id="time" name="time">
    <listOfUnits>
      <unit metaid="_324636" kind="second" multiplier="3600"/>
    </listOfUnits>
  </unitDefinition>
</listOfUnitDefinitions><listOfCompartments>
  <compartment metaid="_658261" id="COMpartment" size="1" units="litre"/>
</listOfCompartments><listOfParameters>
  <parameter metaid="_658284" id="Qv" name="Qv" constant="false"/>
  <parameter metaid="_658285" id="Vv" name="Vv" value="0" constant="false"/>
  <parameter metaid="_658288" id="tau_v" name="tau_v" value="10"/>
  <parameter metaid="_658290" id="v_vm" name="v_vm" value="-1.9"/>
  <parameter metaid="_658292" id="Qa" name="Qa" constant="false"/>
  <parameter metaid="_658294" id="Va" name="Va" constant="false"/>
  <parameter metaid="_658296" id="Vao" name="Vao" value="1"/>
  <parameter metaid="_658298" id="Qm" name="Qm" constant="false"/>
  <parameter metaid="_658300" id="Vm" name="Vm" value="0" constant="false"/>
  <parameter metaid="_658302" id="tau_m" name="tau_m" value="10"/>
  <parameter metaid="_658304" id="v_mv" name="v_mv" value="-1.9"/>
  <parameter metaid="_658306" id="v_maQao" name="v_maQao" value="1"/>
  <parameter metaid="_658308" id="H" name="H" value="15" constant="false"/>
  <parameter metaid="_658310" id="chi" name="chi" value="10.8"/>
  <parameter metaid="_658312" id="mu" name="mu" value="3.6"/>
  <parameter metaid="_658314" id="D" name="D" constant="false"/>
  <parameter metaid="_658316" id="C" name="C" constant="false"/>
  <parameter metaid="_658318" id="c0" name="c0" value="1"/>
  <parameter metaid="_658320" id="omega" name="omega" constant="false"/>
  <parameter metaid="_658322" id="v_vc" name="v_vc" value="-6.3"/>
  <parameter metaid="_658324" id="v_vh" name="v_vh" value="0.19"/>
  <parameter metaid="_658326" id="Qmax" name="Qmax" value="100"/>
  <parameter metaid="_658328" id="theta" name="theta" value="10"/>
  <parameter metaid="_658330" id="sigma" name="sigma" value="3"/>
</listOfParameters><listOfRules>
  <rateRule metaid="_658265" variable="Vv">
    <math xmlns="http://www.w3.org/1998/Math/MathML">
      <apply>
        <divide/>
        <apply>
          <minus/>
          <apply>
            <plus/>
            <apply>
              <times/>
              <ci> v_vm </ci>
              <ci> Qm </ci>
            </apply>
            <ci> D </ci>
          </apply>
          <ci> Vv </ci>
        </apply>
        <apply>
          <divide/>
          <ci> tau_v </ci>
          <cn> 3600 </cn>
        </apply>
      </apply>
    </math>
  </rateRule>
  <rateRule metaid="_658266" variable="Vm">
    <math xmlns="http://www.w3.org/1998/Math/MathML">
      <apply>
        <divide/>
        <apply>
          <minus/>
          <apply>
            <plus/>
            <ci> v_maQao </ci>
            <apply>
              <times/>
              <ci> v_mv </ci>
              <ci> Qv </ci>
            </apply>
          </apply>
          <ci> Vm </ci>
        </apply>
        <apply>
          <divide/>
          <ci> tau_m </ci>
          <cn> 3600 </cn>
        </apply>
      </apply>
    </math>
  </rateRule>
  <rateRule metaid="_658268" variable="H">
    <math xmlns="http://www.w3.org/1998/Math/MathML">
      <apply>
        <divide/>
        <apply>
          <minus/>
          <apply>
            <times/>
            <ci> mu </ci>
            <ci> Qm </ci>
          </apply>
          <ci> H </ci>
        </apply>
        <ci> chi </ci>
      </apply>
    </math>
  </rateRule>
  <assignmentRule metaid="_658270" variable="Qv">
    <math xmlns="http://www.w3.org/1998/Math/MathML">
      <apply>
        <divide/>
        <ci> Qmax </ci>
        <apply>
          <plus/>
          <cn> 1 </cn>
          <apply>
            <exp/>
            <apply>
              <divide/>
              <apply>
                <minus/>
                <apply>
                  <minus/>
                  <ci> Vv </ci>
                  <ci> theta </ci>
                </apply>
              </apply>
              <ci> sigma </ci>
            </apply>
          </apply>
        </apply>
      </apply>
    </math>
  </assignmentRule>
  <assignmentRule metaid="_658272" variable="Qa">
    <math xmlns="http://www.w3.org/1998/Math/MathML">
      <apply>
        <divide/>
        <ci> Qmax </ci>
        <apply>
          <plus/>
          <cn> 1 </cn>
          <apply>
            <exp/>
            <apply>
              <divide/>
              <apply>
                <minus/>
                <apply>
                  <minus/>
                  <ci> Va </ci>
                  <ci> theta </ci>
                </apply>
              </apply>
              <ci> sigma </ci>
            </apply>
          </apply>
        </apply>
      </apply>
    </math>
  </assignmentRule>
  <assignmentRule metaid="_658274" variable="Va">
    <math xmlns="http://www.w3.org/1998/Math/MathML">
      <ci> Vao </ci>
    </math>
  </assignmentRule>
  <assignmentRule metaid="_658276" variable="Qm">
    <math xmlns="http://www.w3.org/1998/Math/MathML">
      <apply>
        <divide/>
        <ci> Qmax </ci>
        <apply>
          <plus/>
          <cn> 1 </cn>
          <apply>
            <exp/>
            <apply>
              <divide/>
              <apply>
                <minus/>
                <apply>
                  <minus/>
                  <ci> Vm </ci>
                  <ci> theta </ci>
                </apply>
              </apply>
              <ci> sigma </ci>
            </apply>
          </apply>
        </apply>
      </apply>
    </math>
  </assignmentRule>
  <assignmentRule metaid="_658278" variable="D">
    <math xmlns="http://www.w3.org/1998/Math/MathML">
      <apply>
        <plus/>
        <apply>
          <times/>
          <ci> v_vc </ci>
          <ci> C </ci>
        </apply>
        <apply>
          <times/>
          <ci> v_vh </ci>
          <ci> H </ci>
        </apply>
      </apply>
    </math>
  </assignmentRule>
  <assignmentRule metaid="_658280" variable="C">
    <math xmlns="http://www.w3.org/1998/Math/MathML">
      <apply>
        <plus/>
        <ci> c0 </ci>
        <apply>
          <cos/>
          <apply>
            <times/>
            <ci> omega </ci>
            <csymbol encoding="text" definitionURL="http://www.sbml.org/sbml/symbols/time"> time </csymbol>
          </apply>
        </apply>
      </apply>
    </math>
  </assignmentRule>
  <assignmentRule metaid="_658282" variable="omega">
    <math xmlns="http://www.w3.org/1998/Math/MathML">
      <apply>
        <divide/>
        <apply>
          <times/>
          <cn> 2 </cn>
          <pi/>
        </apply>
        <cn> 24 </cn>
      </apply>
    </math>
  </assignmentRule>
</listOfRules>
</model>
</sbml>
