<!DOCTYPE article PUBLIC "" ""><sbml xmlns="http://www.sbml.org/sbml/level2" level="2" metaid="metaid_0000001"
      version="1">
  <model id="model_0000001" metaid="metaid_0000002" name="Legewie et al. Model 2">
      <annotation>
         <rdf:RDF xmlns:dc="http://purl.org/dc/elements/1.1/"
                  xmlns:dcterms="http://purl.org/dc/terms/"
                  xmlns:rdf="http://www.w3.org/1999/02/22-rdf-syntax-ns#"
                  xmlns:vCard="http://www.w3.org/2001/vcard-rdf/3.0#">
            <rdf:Description rdf:about="#metaid_0000002">
               <dc:creator rdf:parseType="Resource">
                  <rdf:Bag>
                     <rdf:li>
                        <vCard:N rdf:parseType="Resource">
                           <vCard:Family>Legewie</vCard:Family>
                           <vCard:Given>Stefan</vCard:Given>
                        </vCard:N>
                        <vCard:EMAIL>s.legewie@biologie.hu-berlin.de</vCard:EMAIL>
                        <vCard:ORG>
                           <vCard:Orgname>Humboldt University Berlin</vCard:Orgname>
                        </vCard:ORG>
                     </rdf:li>
                     <rdf:li>
                        <vCard:N rdf:parseType="Resource">
                           <vCard:Family>Bluethgen</vCard:Family>
                           <vCard:Given>Nils</vCard:Given>
                        </vCard:N>
                        <vCard:EMAIL>nils@itb.biologie.hu-berlin.de</vCard:EMAIL>
                        <vCard:ORG>
                           <vCard:Orgname>Humboldt University Berlin</vCard:Orgname>
                        </vCard:ORG>
                     </rdf:li>
                     <rdf:li>
                        <vCard:N rdf:parseType="Resource">
                           <vCard:Family>Herzel</vCard:Family>
                           <vCard:Given>Hanspeter</vCard:Given>
                        </vCard:N>
                        <vCard:EMAIL>h.herzel@biologie.hu-berlin.de</vCard:EMAIL>
                        <vCard:ORG>
                           <vCard:Orgname>Humboldt Universtity Berlin</vCard:Orgname>
                        </vCard:ORG>
                     </rdf:li>
                  </rdf:Bag>
               </dc:creator>
               <dcterms:created rdf:parseType="Resource">
                  <dcterms:W3CDTF>2006-04-20T11:59:50</dcterms:W3CDTF>
               </dcterms:created>
               <dcterms:modified rdf:parseType="Resource">
                  <dcterms:W3CDTF>2006-04-20T13:27:31</dcterms:W3CDTF>
               </dcterms:modified>
            </rdf:Description>
         </rdf:RDF>
      </annotation>


      <listOfCompartments>
         <compartment id="cytosol" metaid="metaid_0000003" name="Cytosol"/>
      </listOfCompartments>

      <listOfSpecies>
         <species compartment="cytosol" id="dummy" initialConcentration="0"
                  metaid="metaid_1000000"
                  name="dummy source and sink"/>

         <species compartment="cytosol" id="A" initialConcentration="20" metaid="metaid_0000004"
                  name="APAF-1"/>
         <species compartment="cytosol" id="C9" initialConcentration="20" metaid="metaid_0000005"
                  name="Caspase 9"/>
         <species compartment="cytosol" id="C9X" initialConcentration="0" metaid="metaid_0000006"
                  name="Caspase 9-XIAP complex"/>
         <species compartment="cytosol" id="X" initialConcentration="40" metaid="metaid_0000007"
                  name="XIAP"/>
         <species compartment="cytosol" id="AC9X" initialConcentration="0"
                  metaid="metaid_0000008"
                  name="APAF-1-Caspase 9-XIAP complex"/>
         <species compartment="cytosol" id="AC9" initialConcentration="0" metaid="metaid_0000009"
                  name="APAF-1-Caspase 9 complex"/>
         <species compartment="cytosol" id="C3" initialConcentration="200"
                  metaid="metaid_0000010"
                  name="Caspase 3"/>
         <species compartment="cytosol" id="C3_star" initialConcentration="0"
                  metaid="metaid_0000011"
                  name="Caspase 3 cleaved"/>
         <species compartment="cytosol" id="C3_starX" initialConcentration="0"
                  metaid="metaid_0000012"
                  name="Caspase 3 cleaved - XIAP complex"/>
         <species compartment="cytosol" id="C9_starX" initialConcentration="0"
                  metaid="metaid_0000013"
                  name="Caspase 9 cleaved-XIAP complex"/>
         <species compartment="cytosol" id="C9_star" initialConcentration="0"
                  metaid="metaid_0000014"
                  name="Caspase 9 cleaved"/>
         <species compartment="cytosol" id="AC9_star" initialConcentration="0"
                  metaid="metaid_0000015"
                  name="APAF-1-Caspase 9 cleaved complex"/>
         <species compartment="cytosol" id="AC9_starX" initialConcentration="0"
                  metaid="metaid_0000016"
                  name="Apaf-1-Caspase 9 cleaved -XIAP complex"/>
         <species compartment="cytosol" id="C9X_C3_star" initialConcentration="0"
                  metaid="metaid_0000045"
                  name="Apaf-1-Caspase 9 cleaved -XIAP complex"/>
         <species compartment="cytosol" id="AC9X_C3_star" initialConcentration="0"
                  metaid="metaid_0000046"
                  name="Apaf-1-Caspase 9 cleaved -XIAP complex"/>
         <species compartment="cytosol" id="C9_starX_C3_star" initialConcentration="0"
                  metaid="metaid_0000047"
                  name="Apaf-1-Caspase 9 cleaved -XIAP complex"/>
         <species compartment="cytosol" id="AC9_starX_C3_star" initialConcentration="0"
                  metaid="metaid_0000048"
                  name="Apaf-1-Caspase 9 cleaved -XIAP complex"/>
      </listOfSpecies>


      <listOfParameters>
         <parameter id="k1" value="0.002"/>
         <parameter id="kb1" value="0.1"/>
         <parameter id="k2" value="0.000005"/>
         <parameter id="k3" value="0.00035"/>
         <parameter id="k9" value="0.001"/>
         <parameter id="k9b" value="0.001"/>
         <parameter id="k10" value="0.001"/>
         <parameter id="k10b" value="0.001"/>
         <parameter id="k13" value="0.002"/>
         <parameter id="k13b" value="0.1"/>
         <parameter id="k15" value="0.003"/>
         <parameter id="k15b" value="0.001"/>
         <parameter id="k4" value="0.0002"/>
         <parameter id="k5" value="0.0002"/>
         <parameter id="k8" value="0.002"/>
         <parameter id="k8b" value="0.1"/>
         <parameter id="k11" value="0.001"/>
         <parameter id="k11b" value="0.001"/>
         <parameter id="k12" value="0.001"/>
         <parameter id="k12b" value="0.001"/>
         <parameter id="k14" value="0.002"/>
         <parameter id="k14b" value="0.1"/>
         <parameter id="k6" value="0.00005"/>
         <parameter id="k7" value="0.0035"/>
         <parameter id="k16" value="0.001"/>
         <parameter id="k16prod" value="0.02"/>
         <parameter id="k17" value="0.001"/>
         <parameter id="k17prod" value="0.02"/>
         <parameter id="k18" value="0.001"/>
         <parameter id="k18prod" value="0.04"/>
         <parameter id="k19" value="0.001"/>
         <parameter id="k20" value="0.001"/>
         <parameter id="k21" value="0.001"/>
         <parameter id="k22" value="0.001"/>
         <parameter id="k22prod" value="0.2"/>
         <parameter id="k23" value="0.001"/>
         <parameter id="k24" value="0.001"/>
         <parameter id="k25" value="0.001"/>
         <parameter id="k26" value="0.001"/>
         <parameter id="k27" value="0.001"/>
         <parameter id="k28" value="0.001"/>
         <parameter id="k29" value="0.001"/>
         <parameter id="k30" value="0.001"/>
         <parameter id="k31" value="0.001"/>
         <parameter id="k32" value="0.001"/>
         <parameter id="a" value="1"/>
         <parameter id="d" value="1"/>
         <parameter id="k41" value="1"/>
         <parameter id="k42" value="1"/>
      </listOfParameters>

      <listOfReactions>

         <reaction fast="false" id="v1" metaid="metaid_0000017" name="Caspase 9 / Apaf-1 binding"
                   reversible="true">
            <listOfReactants>
               <speciesReference species="A" stoichiometry="1"/>
               <speciesReference species="C9" stoichiometry="1"/>
            </listOfReactants>
            <listOfProducts>
               <speciesReference species="AC9" stoichiometry="1"/>
            </listOfProducts>
            <kineticLaw>
               <math xmlns="http://www.w3.org/1998/Math/MathML">
                  <apply>
                     <minus/>
                     <apply>
                        <times/>
                        <ci> k1 </ci>
                        <ci> A </ci>
                        <ci> C9 </ci>
                     </apply>
                     <apply>
                        <times/>
                        <ci> kb1 </ci>
                        <ci> AC9 </ci>
                     </apply>
                  </apply>
               </math>
            </kineticLaw>
         </reaction>

         <reaction fast="false" id="v2" metaid="metaid_0000018"
                   name="Caspase 3 cleavage by Caspase 9"
                   reversible="false">
            <listOfReactants>
               <speciesReference species="C3" stoichiometry="1"/>
               <speciesReference species="C9" stoichiometry="1"/>
            </listOfReactants>
            <listOfProducts>
               <speciesReference species="C3_star" stoichiometry="1"/>
               <speciesReference species="C9" stoichiometry="1"/>
            </listOfProducts>
            <kineticLaw>
               <math xmlns="http://www.w3.org/1998/Math/MathML">
                  <apply>
                     <times/>
                     <ci> k2 </ci>
                     <ci> C3 </ci>
                     <ci> C9 </ci>
                  </apply>
               </math>
            </kineticLaw>
         </reaction>

         <reaction fast="false" id="v3" metaid="metaid_0000019"
                   name="Caspase 3 cleavage by Caspase 9-Apaf-1"
                   reversible="false">
            <listOfReactants>
               <speciesReference species="C3" stoichiometry="1"/>
               <speciesReference species="AC9" stoichiometry="1"/>
            </listOfReactants>
            <listOfProducts>
               <speciesReference species="C3_star" stoichiometry="1"/>
               <speciesReference species="AC9" stoichiometry="1"/>
            </listOfProducts>
            <kineticLaw>
               <math xmlns="http://www.w3.org/1998/Math/MathML">
                  <apply>
                     <times/>
                     <ci> k3 </ci>
                     <ci> C3 </ci>
                     <ci> AC9 </ci>
                  </apply>
               </math>
            </kineticLaw>
         </reaction>

         <reaction fast="false" id="v9" metaid="metaid_0000020" name="Caspase 9 Xiap binding"
                   reversible="true">
            <listOfReactants>
               <speciesReference species="C9" stoichiometry="1"/>
               <speciesReference species="X" stoichiometry="1"/>
            </listOfReactants>
            <listOfProducts>
               <speciesReference species="C9X" stoichiometry="1"/>
            </listOfProducts>
            <kineticLaw>
               <math xmlns="http://www.w3.org/1998/Math/MathML">
                  <apply>
                     <minus/>
                     <apply>
                        <times/>
                        <ci> k9 </ci>
                        <ci> C9 </ci>
                        <ci> X </ci>
                     </apply>
                     <apply>
                        <times/>
                        <ci> k9b </ci>
                        <ci> C9X </ci>
                     </apply>
                  </apply>
               </math>
            </kineticLaw>
         </reaction>

         <reaction fast="false" id="v10" metaid="metaid_0000021"
                   name="Caspase 9-Apaf-1 Xiap binding"
                   reversible="true">
            <listOfReactants>
               <speciesReference species="AC9" stoichiometry="1"/>
               <speciesReference species="X" stoichiometry="1"/>
            </listOfReactants>
            <listOfProducts>
               <speciesReference species="AC9X" stoichiometry="1"/>
            </listOfProducts>
            <kineticLaw>
               <math xmlns="http://www.w3.org/1998/Math/MathML">
                  <apply>
                     <minus/>
                     <apply>
                        <times/>
                        <ci> k10 </ci>
                        <ci> AC9 </ci>
                        <ci> X </ci>
                     </apply>
                     <apply>
                        <times/>
                        <ci> k10b </ci>
                        <ci> AC9X </ci>
                     </apply>
                  </apply>
               </math>
            </kineticLaw>
         </reaction>

         <reaction fast="false" id="v13" metaid="metaid_0000022"
                   name="Caspase 9-Xiap Apaf-1 binding"
                   reversible="true">
            <listOfReactants>
               <speciesReference species="C9X" stoichiometry="1"/>
               <speciesReference species="A" stoichiometry="1"/>
            </listOfReactants>
            <listOfProducts>
               <speciesReference species="AC9X" stoichiometry="1"/>
            </listOfProducts>
            <kineticLaw>
               <math xmlns="http://www.w3.org/1998/Math/MathML">
                  <apply>
                     <minus/>
                     <apply>
                        <times/>
                        <ci> k13 </ci>
                        <ci> C9X </ci>
                        <ci> A </ci>
                     </apply>
                     <apply>
                        <times/>
                        <ci> k13b </ci>
                        <ci> AC9X </ci>
                     </apply>
                  </apply>
               </math>
            </kineticLaw>
         </reaction>

         <reaction fast="false" id="v15" metaid="metaid_0000023"
                   name="cleaved Caspase 3-Xiap binding"
                   reversible="true">
            <listOfReactants>
               <speciesReference species="C3_star" stoichiometry="1"/>
               <speciesReference species="X" stoichiometry="1"/>
            </listOfReactants>
            <listOfProducts>
               <speciesReference species="C3_starX" stoichiometry="1"/>
            </listOfProducts>
            <kineticLaw>
               <math xmlns="http://www.w3.org/1998/Math/MathML">
                  <apply>
                     <minus/>
                     <apply>
                        <times/>
                        <ci> k15 </ci>
                        <ci> C3_star </ci>
                        <ci> X </ci>
                     </apply>
                     <apply>
                        <times/>
                        <ci> k15b </ci>
                        <ci> C3_starX </ci>
                     </apply>
                  </apply>
               </math>
            </kineticLaw>
         </reaction>

         <reaction fast="false" id="v4" metaid="metaid_0000024"
                   name="Caspase 9 cleavage by cleaved caspase 3"
                   reversible="false">
            <listOfReactants>
               <speciesReference species="C9" stoichiometry="1"/>
               <speciesReference species="C3_star" stoichiometry="1"/>
            </listOfReactants>
            <listOfProducts>
               <speciesReference species="C9_star" stoichiometry="1"/>
               <speciesReference species="C3_star" stoichiometry="1"/>
            </listOfProducts>
            <kineticLaw>
               <math xmlns="http://www.w3.org/1998/Math/MathML">
                  <apply>
                     <times/>
                     <ci> k4 </ci>
                     <ci> C9 </ci>
                     <ci> C3_star </ci>
                  </apply>
               </math>
            </kineticLaw>
         </reaction>

         <reaction fast="false" id="v5" metaid="metaid_0000025"
                   name="Caspase 9 cleavage by cleaved caspase 3 when Apaf-1 is bound"
                   reversible="false">
            <listOfReactants>
               <speciesReference species="AC9" stoichiometry="1"/>
               <speciesReference species="C3_star" stoichiometry="1"/>
            </listOfReactants>
            <listOfProducts>
               <speciesReference species="AC9_star" stoichiometry="1"/>
               <speciesReference species="C3_star" stoichiometry="1"/>
            </listOfProducts>
            <kineticLaw>
               <math xmlns="http://www.w3.org/1998/Math/MathML">
                  <apply>
                     <times/>
                     <ci> k5 </ci>
                     <ci> AC9 </ci>
                     <ci> C3_star </ci>
                  </apply>
               </math>
            </kineticLaw>
         </reaction>

         <reaction fast="false" id="v8" metaid="metaid_0000026"
                   name="cleaved Caspase 9 Apaf-1 binding"
                   reversible="true">
            <listOfReactants>
               <speciesReference species="C9_star" stoichiometry="1"/>
               <speciesReference species="A" stoichiometry="1"/>
            </listOfReactants>
            <listOfProducts>
               <speciesReference species="AC9_star" stoichiometry="1"/>
            </listOfProducts>
            <kineticLaw>
               <math xmlns="http://www.w3.org/1998/Math/MathML">
                  <apply>
                     <minus/>
                     <apply>
                        <times/>
                        <ci> k8 </ci>
                        <ci> C9_star </ci>
                        <ci> A </ci>
                     </apply>
                     <apply>
                        <times/>
                        <ci> k8b </ci>
                        <ci> AC9_star </ci>
                     </apply>
                  </apply>
               </math>
            </kineticLaw>
         </reaction>

         <reaction fast="false" id="v11" metaid="metaid_0000027"
                   name="cleaved Caspase 9 XIAP binding"
                   reversible="true">
            <listOfReactants>
               <speciesReference species="C9_star" stoichiometry="1"/>
               <speciesReference species="X" stoichiometry="1"/>
            </listOfReactants>
            <listOfProducts>
               <speciesReference species="C9_starX" stoichiometry="1"/>
            </listOfProducts>
            <kineticLaw>
               <math xmlns="http://www.w3.org/1998/Math/MathML">
                  <apply>
                     <minus/>
                     <apply>
                        <times/>
                        <ci> k11 </ci>
                        <ci> C9_star </ci>
                        <ci> X </ci>
                     </apply>
                     <apply>
                        <times/>
                        <ci> k11b </ci>
                        <ci> C9_starX </ci>
                     </apply>
                  </apply>
               </math>
            </kineticLaw>
         </reaction>

         <reaction fast="false" id="v12" metaid="metaid_0000028"
                   name="cleaved Caspase 9-Apaf-1 XIAP binding"
                   reversible="true">
            <listOfReactants>
               <speciesReference species="AC9_star" stoichiometry="1"/>
               <speciesReference species="X" stoichiometry="1"/>
            </listOfReactants>
            <listOfProducts>
               <speciesReference species="AC9_starX" stoichiometry="1"/>
            </listOfProducts>
            <kineticLaw>
               <math xmlns="http://www.w3.org/1998/Math/MathML">
                  <apply>
                     <minus/>
                     <apply>
                        <times/>
                        <ci> k12 </ci>
                        <ci> AC9_star </ci>
                        <ci> X </ci>
                     </apply>
                     <apply>
                        <times/>
                        <ci> k12b </ci>
                        <ci> AC9_starX </ci>
                     </apply>
                  </apply>
               </math>
            </kineticLaw>
         </reaction>

         <reaction fast="false" id="v14" metaid="metaid_0000029"
                   name="cleaved Caspase 9-Xiap Apaf-1 binding"
                   reversible="true">
            <listOfReactants>
               <speciesReference species="C9_starX" stoichiometry="1"/>
               <speciesReference species="A" stoichiometry="1"/>
            </listOfReactants>
            <listOfProducts>
               <speciesReference species="AC9_starX" stoichiometry="1"/>
            </listOfProducts>
            <kineticLaw>
               <math xmlns="http://www.w3.org/1998/Math/MathML">
                  <apply>
                     <minus/>
                     <apply>
                        <times/>
                        <ci> k14 </ci>
                        <ci> C9_starX </ci>
                        <ci> A </ci>
                     </apply>
                     <apply>
                        <times/>
                        <ci> k14b </ci>
                        <ci> AC9_starX </ci>
                     </apply>
                  </apply>
               </math>
            </kineticLaw>
         </reaction>

         <reaction fast="false" id="v6" metaid="metaid_0000030"
                   name="Caspase 3 cleavage by cleaved Caspase 9"
                   reversible="false">
            <listOfReactants>
               <speciesReference species="C3" stoichiometry="1"/>
               <speciesReference species="C9_star" stoichiometry="1"/>
            </listOfReactants>
            <listOfProducts>
               <speciesReference species="C3_star" stoichiometry="1"/>
               <speciesReference species="C9_star" stoichiometry="1"/>
            </listOfProducts>
            <kineticLaw>
               <math xmlns="http://www.w3.org/1998/Math/MathML">
                  <apply>
                     <times/>
                     <ci> k6 </ci>
                     <ci> C3 </ci>
                     <ci> C9_star </ci>
                  </apply>
               </math>
            </kineticLaw>
         </reaction>

         <reaction fast="false" id="v7" metaid="metaid_0000031"
                   name="Caspase 3 cleavage by cleaved Caspase 9 - Apaf-1"
                   reversible="false">
            <listOfReactants>
               <speciesReference species="C3" stoichiometry="1"/>
               <speciesReference species="AC9_star" stoichiometry="1"/>
            </listOfReactants>
            <listOfProducts>
               <speciesReference species="C3_star" stoichiometry="1"/>
               <speciesReference species="AC9_star" stoichiometry="1"/>
            </listOfProducts>
            <kineticLaw>
               <math xmlns="http://www.w3.org/1998/Math/MathML">
                  <apply>
                     <times/>
                     <ci> k7 </ci>
                     <ci> C3 </ci>
                     <ci> AC9_star </ci>
                  </apply>
               </math>
            </kineticLaw>
         </reaction>

         <reaction fast="false" id="v16" metaid="metaid_0000032" name="Apaf-1 turnover"
                   reversible="true">
            <listOfReactants>
               <speciesReference species="dummy" stoichiometry="1"/>
            </listOfReactants>
            <listOfProducts>
               <speciesReference species="A" stoichiometry="1"/>
            </listOfProducts>
            <kineticLaw>
               <math xmlns="http://www.w3.org/1998/Math/MathML">
                  <apply>
                     <minus/>
                     <apply>
                        <times/>
                        <ci> k16prod </ci>
                     </apply>
                     <apply>
                        <times/>
                        <ci> k16 </ci>
                        <ci> A </ci>
                     </apply>
                  </apply>
               </math>
            </kineticLaw>
         </reaction>

         <reaction fast="false" id="v17" metaid="metaid_0000033" name="Caspase 9 turnover"
                   reversible="true">
            <listOfReactants>
               <speciesReference species="dummy" stoichiometry="1"/>
            </listOfReactants>
            <listOfProducts>
               <speciesReference species="C9" stoichiometry="1"/>
            </listOfProducts>
            <kineticLaw>
               <math xmlns="http://www.w3.org/1998/Math/MathML">
                  <apply>
                     <minus/>
                     <apply>
                        <times/>
                        <ci> k17prod </ci>
                     </apply>
                     <apply>
                        <times/>
                        <ci> k17 </ci>
                        <ci> C9 </ci>
                     </apply>
                  </apply>
               </math>
            </kineticLaw>
         </reaction>

         <reaction fast="false" id="v18" metaid="metaid_0000034" name="Xiap turnover"
                   reversible="true">
            <listOfReactants>
               <speciesReference species="dummy" stoichiometry="1"/>
            </listOfReactants>
            <listOfProducts>
               <speciesReference species="X" stoichiometry="1"/>
            </listOfProducts>
            <kineticLaw>
               <math xmlns="http://www.w3.org/1998/Math/MathML">
                  <apply>
                     <minus/>
                     <apply>
                        <times/>
                        <ci> k18prod </ci>
                     </apply>
                     <apply>
                        <times/>
                        <ci> k18 </ci>
                        <ci> X </ci>
                     </apply>
                  </apply>
               </math>
            </kineticLaw>
         </reaction>

         <reaction fast="false" id="v19" metaid="metaid_0000035" name="Caspase 9-Xiap degradation"
                   reversible="false">
            <listOfReactants>
               <speciesReference species="C9X" stoichiometry="1"/>
            </listOfReactants>
            <listOfProducts>
               <speciesReference species="dummy" stoichiometry="1"/>
            </listOfProducts>
            <kineticLaw>
               <math xmlns="http://www.w3.org/1998/Math/MathML">
                  <apply>
                     <times/>
                     <ci> k19 </ci>
                     <ci> C9X </ci>
                  </apply>
               </math>
            </kineticLaw>
         </reaction>

         <reaction fast="false" id="v20" metaid="metaid_0000036"
                   name="Apaf-1-Caspase 9-Xiap degradation"
                   reversible="false">
            <listOfReactants>
               <speciesReference species="AC9X" stoichiometry="1"/>
            </listOfReactants>
            <listOfProducts>
               <speciesReference species="dummy" stoichiometry="1"/>
            </listOfProducts>
            <kineticLaw>
               <math xmlns="http://www.w3.org/1998/Math/MathML">
                  <apply>
                     <times/>
                     <ci> k20 </ci>
                     <ci> AC9X </ci>
                  </apply>
               </math>
            </kineticLaw>
         </reaction>

         <reaction fast="false" id="v21" metaid="metaid_0000037"
                   name="Apaf-1-Caspase 9 degradation"
                   reversible="false">
            <listOfReactants>
               <speciesReference species="AC9" stoichiometry="1"/>
            </listOfReactants>
            <listOfProducts>
               <speciesReference species="dummy" stoichiometry="1"/>
            </listOfProducts>
            <kineticLaw>
               <math xmlns="http://www.w3.org/1998/Math/MathML">
                  <apply>
                     <times/>
                     <ci> k21 </ci>
                     <ci> AC9 </ci>
                  </apply>
               </math>
            </kineticLaw>
         </reaction>

         <reaction fast="false" id="v22" metaid="metaid_0000038" name="Caspase 3 turnover"
                   reversible="true">
            <listOfReactants>
               <speciesReference species="dummy" stoichiometry="1"/>
            </listOfReactants>
            <listOfProducts>
               <speciesReference species="C3" stoichiometry="1"/>
            </listOfProducts>
            <kineticLaw>
               <math xmlns="http://www.w3.org/1998/Math/MathML">
                  <apply>
                     <minus/>
                     <apply>
                        <times/>
                        <ci> k22prod </ci>
                     </apply>
                     <apply>
                        <times/>
                        <ci> k22 </ci>
                        <ci> C3 </ci>
                     </apply>
                  </apply>
               </math>
            </kineticLaw>
         </reaction>

         <reaction fast="false" id="v23" metaid="metaid_0000039"
                   name="Caspase 3 cleaved degradation"
                   reversible="false">
            <listOfReactants>
               <speciesReference species="C3_star" stoichiometry="1"/>
            </listOfReactants>
            <listOfProducts>
               <speciesReference species="dummy" stoichiometry="1"/>
            </listOfProducts>
            <kineticLaw>
               <math xmlns="http://www.w3.org/1998/Math/MathML">
                  <apply>
                     <times/>
                     <ci> k23 </ci>
                     <ci> C3_star </ci>
                  </apply>
               </math>
            </kineticLaw>
         </reaction>

         <reaction fast="false" id="v24" metaid="metaid_0000040"
                   name="Caspase 3 cleaved-Xiap degradation"
                   reversible="false">
            <listOfReactants>
               <speciesReference species="C3_starX" stoichiometry="1"/>
            </listOfReactants>
            <listOfProducts>
               <speciesReference species="dummy" stoichiometry="1"/>
            </listOfProducts>
            <kineticLaw>
               <math xmlns="http://www.w3.org/1998/Math/MathML">
                  <apply>
                     <times/>
                     <ci> k24 </ci>
                     <ci> C3_starX </ci>
                  </apply>
               </math>
            </kineticLaw>
         </reaction>

         <reaction fast="false" id="v25" metaid="metaid_0000041"
                   name="Caspase 9 cleaved-Xiap degradation"
                   reversible="false">
            <listOfReactants>
               <speciesReference species="C9_starX" stoichiometry="1"/>
            </listOfReactants>
            <listOfProducts>
               <speciesReference species="dummy" stoichiometry="1"/>
            </listOfProducts>
            <kineticLaw>
               <math xmlns="http://www.w3.org/1998/Math/MathML">
                  <apply>
                     <times/>
                     <ci> k25 </ci>
                     <ci> C9_starX </ci>
                  </apply>
               </math>
            </kineticLaw>
         </reaction>

         <reaction fast="false" id="v26" metaid="metaid_0000042"
                   name="Caspase 9 cleaved degradation"
                   reversible="false">
            <listOfReactants>
               <speciesReference species="C9_star" stoichiometry="1"/>
            </listOfReactants>
            <listOfProducts>
               <speciesReference species="dummy" stoichiometry="1"/>
            </listOfProducts>
            <kineticLaw>
               <math xmlns="http://www.w3.org/1998/Math/MathML">
                  <apply>
                     <times/>
                     <ci> k26 </ci>
                     <ci> C9_star </ci>
                  </apply>
               </math>
            </kineticLaw>
         </reaction>

         <reaction fast="false" id="v27" metaid="metaid_0000043"
                   name="Apaf-1 Caspase 9 cleaved degradation"
                   reversible="false">
            <listOfReactants>
               <speciesReference species="AC9_star" stoichiometry="1"/>
            </listOfReactants>
            <listOfProducts>
               <speciesReference species="dummy" stoichiometry="1"/>
            </listOfProducts>
            <kineticLaw>
               <math xmlns="http://www.w3.org/1998/Math/MathML">
                  <apply>
                     <times/>
                     <ci> k27 </ci>
                     <ci> AC9_star </ci>
                  </apply>
               </math>
            </kineticLaw>
         </reaction>

         <reaction fast="false" id="v28" metaid="metaid_0000044"
                   name="Apaf-1 Caspase 9 cleaved-Xiap degradation"
                   reversible="false">
            <listOfReactants>
               <speciesReference species="AC9_starX" stoichiometry="1"/>
            </listOfReactants>
            <listOfProducts>
               <speciesReference species="dummy" stoichiometry="1"/>
            </listOfProducts>
            <kineticLaw>
               <math xmlns="http://www.w3.org/1998/Math/MathML">
                  <apply>
                     <times/>
                     <ci> k28 </ci>
                     <ci> AC9_starX </ci>
                  </apply>
               </math>
            </kineticLaw>
         </reaction>

         <reaction fast="false" id="v29" metaid="metaid_0000049"
                   name="Caspase9-Xiap-Caspase3_star degradation"
                   reversible="false">
            <listOfReactants>
               <speciesReference species="C9X_C3_star" stoichiometry="1"/>
            </listOfReactants>
            <listOfProducts>
               <speciesReference species="dummy" stoichiometry="1"/>
            </listOfProducts>
            <kineticLaw>
               <math xmlns="http://www.w3.org/1998/Math/MathML">
                  <apply>
                     <times/>
                     <ci> k29 </ci>
                     <ci> C9X_C3_star </ci>
                  </apply>
               </math>
            </kineticLaw>
         </reaction>

         <reaction fast="false" id="v30" metaid="metaid_0000050"
                   name="Apaf-1-Caspase9-Xiap-Caspase3_star degradation"
                   reversible="false">
            <listOfReactants>
               <speciesReference species="AC9_starX_C3_star" stoichiometry="1"/>
            </listOfReactants>
            <listOfProducts>
               <speciesReference species="dummy" stoichiometry="1"/>
            </listOfProducts>
            <kineticLaw>
               <math xmlns="http://www.w3.org/1998/Math/MathML">
                  <apply>
                     <times/>
                     <ci> k30 </ci>
                     <ci> AC9_starX_C3_star </ci>
                  </apply>
               </math>
            </kineticLaw>
         </reaction>

         <reaction fast="false" id="v31" metaid="metaid_0000051"
                   name="Caspase9_star-Xiap-Caspase3_star degradation"
                   reversible="false">
            <listOfReactants>
               <speciesReference species="C9_starX_C3_star" stoichiometry="1"/>
            </listOfReactants>
            <listOfProducts>
               <speciesReference species="dummy" stoichiometry="1"/>
            </listOfProducts>
            <kineticLaw>
               <math xmlns="http://www.w3.org/1998/Math/MathML">
                  <apply>
                     <times/>
                     <ci> k31 </ci>
                     <ci> C9_starX_C3_star </ci>
                  </apply>
               </math>
            </kineticLaw>
         </reaction>

         <reaction fast="false" id="v32" metaid="metaid_0000052"
                   name="Apaf-1-Caspase9_star-Xiap-Caspase3_star degradation"
                   reversible="false">
            <listOfReactants>
               <speciesReference species="C9_starX_C3_star" stoichiometry="1"/>
            </listOfReactants>
            <listOfProducts>
               <speciesReference species="dummy" stoichiometry="1"/>
            </listOfProducts>
            <kineticLaw>
               <math xmlns="http://www.w3.org/1998/Math/MathML">
                  <apply>
                     <times/>
                     <ci> k32 </ci>
                     <ci> AC9_starX_C3_star </ci>
                  </apply>
               </math>
            </kineticLaw>
         </reaction>


         <reaction fast="false" id="v33" metaid="metaid_0000053"
                   name="Cleaved-Caspase 3 binding with Xiap-Caspase 9"
                   reversible="true">
            <listOfReactants>
               <speciesReference species="C3_star" stoichiometry="1"/>
               <speciesReference species="C9X" stoichiometry="1"/>
            </listOfReactants>
            <listOfProducts>
               <speciesReference species="C9X_C3_star" stoichiometry="1"/>
            </listOfProducts>
            <kineticLaw>
               <math xmlns="http://www.w3.org/1998/Math/MathML">
                  <apply>
                     <minus/>
                     <apply>
                        <times/>
                        <ci> a </ci>
                        <ci> k7 </ci>
                        <ci> C3_STAR </ci>
                        <ci> C9X </ci>
                     </apply>
                     <apply>
                        <times/>
                        <ci> d </ci>
                        <ci> k7b </ci>
                        <ci> C9X_C3_star </ci>
                     </apply>
                  </apply>
               </math>
            </kineticLaw>
         </reaction>

         <reaction fast="false" id="v34" metaid="metaid_0000054"
                   name="Cleaved-Caspase 3 binding with Apaf-Xiap-Caspase 9"
                   reversible="true">
            <listOfReactants>
               <speciesReference species="C3_star" stoichiometry="1"/>
               <speciesReference species="AC9X" stoichiometry="1"/>
            </listOfReactants>
            <listOfProducts>
               <speciesReference species="AC9X_C3_star" stoichiometry="1"/>
            </listOfProducts>
            <kineticLaw>
               <math xmlns="http://www.w3.org/1998/Math/MathML">
                  <apply>
                     <minus/>
                     <apply>
                        <times/>
                        <ci> a </ci>
                        <ci> k7 </ci>
                        <ci> C3_star </ci>
                        <ci> AC9X </ci>
                     </apply>
                     <apply>
                        <times/>
                        <ci> d </ci>
                        <ci> k7b </ci>
                        <ci> AC9X_C3_star </ci>
                     </apply>
                  </apply>
               </math>
            </kineticLaw>
         </reaction>

         <reaction fast="false" id="v35" metaid="metaid_0000055"
                   name="Cleaved-Caspase 3 binding with Cleaved-Xiap-Caspase 9"
                   reversible="true">
            <listOfReactants>
               <speciesReference species="C3_star" stoichiometry="1"/>
               <speciesReference species="C9_starX" stoichiometry="1"/>
            </listOfReactants>
            <listOfProducts>
               <speciesReference species="C9_starX_C3_star" stoichiometry="1"/>
            </listOfProducts>
            <kineticLaw>
               <math xmlns="http://www.w3.org/1998/Math/MathML">
                  <apply>
                     <minus/>
                     <apply>
                        <times/>
                        <ci> a </ci>
                        <ci> k7 </ci>
                        <ci> C3_star </ci>
                        <ci> C9_starX </ci>
                     </apply>
                     <apply>
                        <times/>
                        <ci> d </ci>
                        <ci> k7b </ci>
                        <ci> C9_starX_C3_star </ci>
                     </apply>
                  </apply>
               </math>
            </kineticLaw>
         </reaction>

         <reaction fast="false" id="v36" metaid="metaid_0000056"
                   name="Apaf-Xiap-cleaved Caspase 9 binding with cleaved Caspase 3"
                   reversible="true">
            <listOfReactants>
               <speciesReference species="C3_star" stoichiometry="1"/>
               <speciesReference species="AC9_starX" stoichiometry="1"/>
            </listOfReactants>
            <listOfProducts>
               <speciesReference species="AC9_starX_C3_star" stoichiometry="1"/>
            </listOfProducts>
            <kineticLaw>
               <math xmlns="http://www.w3.org/1998/Math/MathML">
                  <apply>
                     <minus/>
                     <apply>
                        <times/>
                        <ci> a </ci>
                        <ci> k7 </ci>
                        <ci> C3_star </ci>
                        <ci> AC9_starX </ci>
                     </apply>
                     <apply>
                        <times/>
                        <ci> d </ci>
                        <ci> k7b </ci>
                        <ci> AC9_starX_C3_star </ci>
                     </apply>
                  </apply>
               </math>
            </kineticLaw>
         </reaction>

         <reaction fast="false" id="v37" metaid="metaid_0000057"
                   name="Binding of Caspase 9 to cleaved Caspase 3-Xiap"
                   reversible="true">
            <listOfReactants>
               <speciesReference species="C9" stoichiometry="1"/>
               <speciesReference species="C3_starX" stoichiometry="1"/>
            </listOfReactants>
            <listOfProducts>
               <speciesReference species="C9X_C3_star" stoichiometry="1"/>
            </listOfProducts>
            <kineticLaw>
               <math xmlns="http://www.w3.org/1998/Math/MathML">
                  <apply>
                     <minus/>
                     <apply>
                        <times/>
                        <ci> a </ci>
                        <ci> k4 </ci>
                        <ci> C9 </ci>
                        <ci> C3_starX </ci>
                     </apply>
                     <apply>
                        <times/>
                        <ci> d </ci>
                        <ci> k4b </ci>
                        <ci> C9X_C3_star </ci>
                     </apply>
                  </apply> 
               </math>
            </kineticLaw>
         </reaction>

         <reaction fast="false" id="v38" metaid="metaid_0000058"
                   name="Binding of Apaf-Caspase 9 to cleaved Caspase 3-Xiap"
                   reversible="true">
            <listOfReactants>
               <speciesReference species="AC9" stoichiometry="1"/>
               <speciesReference species="C3_starX" stoichiometry="1"/>
            </listOfReactants>
            <listOfProducts>
               <speciesReference species="AC9X_C3_star" stoichiometry="1"/>
            </listOfProducts>
            <kineticLaw>
               <math xmlns="http://www.w3.org/1998/Math/MathML">
                  <apply>
                     <minus/>
                     <apply>
                        <times/>
                        <ci> a </ci>
                        <ci> k4 </ci>
                        <ci> AC9 </ci>
                        <ci> C3_starX </ci>
                     </apply>
                     <apply>
                        <times/>
                        <ci> d </ci>
                        <ci> k4b </ci>
                        <ci> AC9X_C3_star </ci>
                     </apply>
                  </apply> 
               </math>
            </kineticLaw>
         </reaction>

         <reaction fast="false" id="v39" metaid="metaid_0000059"
                   name="Binding of cleaved Caspase 9 to cleaved Caspase 3-Xiap"
                   reversible="true">
            <listOfReactants>
               <speciesReference species="C9_star" stoichiometry="1"/>
               <speciesReference species="C3_starX" stoichiometry="1"/>
            </listOfReactants>
            <listOfProducts>
               <speciesReference species="C9_starX_C3_star" stoichiometry="1"/>
            </listOfProducts>
            <kineticLaw>
               <math xmlns="http://www.w3.org/1998/Math/MathML">
                  <apply>
                     <minus/>
                     <apply>
                        <times/>
                        <ci> a </ci>
                        <ci> k4 </ci>
                        <ci> C9_star </ci>
                        <ci> C3_starX </ci>
                     </apply>
                     <apply>
                        <times/>
                        <ci> d </ci>
                        <ci> k4b </ci>
                        <ci> C9_starX_C3_star </ci>
                     </apply>
                  </apply> 
               </math>
            </kineticLaw>
         </reaction>

         <reaction fast="false" id="v40" metaid="metaid_0000060"
                   name="Binding of cleaved Caspase 9-Apaf-1 to cleaved Caspase 3-Xiap"
                   reversible="true">
            <listOfReactants>
               <speciesReference species="AC9_star" stoichiometry="1"/>
               <speciesReference species="C3_starX" stoichiometry="1"/>
            </listOfReactants>
            <listOfProducts>
               <speciesReference species="AC9_starX_C3_star" stoichiometry="1"/>
            </listOfProducts>
            <kineticLaw>
               <math xmlns="http://www.w3.org/1998/Math/MathML">
                  <apply>
                     <minus/>
                     <apply>
                        <times/>
                        <ci> a </ci>
                        <ci> k4 </ci>
                        <ci> AC9_star </ci>
                        <ci> C3_starX </ci>
                     </apply>
                     <apply>
                        <times/>
                        <ci> d </ci>
                        <ci> k4b </ci>
                        <ci> AC9_starX_C3_star </ci>
                     </apply>
                  </apply> 
               </math>
            </kineticLaw>
         </reaction>

         <reaction fast="false" id="v41" metaid="metaid_0000061"
                   name="Binding of Caspase 9-Xiap-cleaved Caspase 3 with Apaf"
                   reversible="true">
            <listOfReactants>
               <speciesReference species="C9X_C3_star" stoichiometry="1"/>
               <speciesReference species="A" stoichiometry="1"/>
            </listOfReactants>
            <listOfProducts>
               <speciesReference species="AC9X_C3_star" stoichiometry="1"/>
            </listOfProducts>
            <kineticLaw>
               <math xmlns="http://www.w3.org/1998/Math/MathML">
                  <apply>
                     <minus/>
                     <apply>
                        <times/>
                        <ci> a </ci>
                        <ci> k1 </ci>
                        <ci> C9X_C3_star </ci>
                        <ci> A </ci>
                     </apply>
                     <apply>
                        <times/>
                        <ci> d </ci>
                        <ci> k1b </ci>
                        <ci> AC9X_C3_star </ci>
                     </apply>
                  </apply> 
               </math>
            </kineticLaw>
         </reaction>

         <reaction fast="false" id="v42" metaid="metaid_0000062"
                   name="Binding of cleaved Caspase 9-Xiap-cleaved Caspase 3 with Apaf"
                   reversible="true">
            <listOfReactants>
               <speciesReference species="C9_starX_C3_star" stoichiometry="1"/>
               <speciesReference species="A" stoichiometry="1"/>
            </listOfReactants>
            <listOfProducts>
               <speciesReference species="AC9_starX_C3_star" stoichiometry="1"/>
            </listOfProducts>
            <kineticLaw>
               <math xmlns="http://www.w3.org/1998/Math/MathML">
                  <apply>
                     <minus/>
                     <apply>
                        <times/>
                        <ci> a </ci>
                        <ci> k1 </ci>
                        <ci> C9_starX_C3_star </ci>
                        <ci> A </ci>
                     </apply>
                     <apply>
                        <times/>
                        <ci> d </ci>
                        <ci> k1b </ci>
                        <ci> AC9_starX_C3_star </ci>
                     </apply>
                  </apply> 
               </math>
            </kineticLaw>
         </reaction>
      </listOfReactions>
   </model>
</sbml>