<?xml version="1.0" encoding="UTF-8"?>
<omexManifest xmlns="http://identifiers.org/combine.specifications/omex-manifest">
  <content location="BIOMD0000000233-biopax2.owl" format="http://purl.org/NET/mediatypes/application/rdf+xml" master="false"/>
  <content location="BIOMD0000000233-biopax3.owl" format="http://purl.org/NET/mediatypes/application/rdf+xml" master="false"/>
  <content location="BIOMD0000000233-matlab.m" format="http://purl.org/NET/mediatypes/text/x-matlab" master="false"/>
  <content location="BIOMD0000000233-octave.m" format="http://purl.org/NET/mediatypes/text/x-matlab" master="false"/>
  <content location="BIOMD0000000233.m" format="http://purl.org/NET/mediatypes/text/x-matlab" master="false"/>
  <content location="BIOMD0000000233.ode" format="http://purl.org/NET/mediatypes/text/x-ode" master="false"/>
  <content location="BIOMD0000000233.pdf" format="http://purl.org/NET/mediatypes/application/PDF" master="false"/>
  <content location="BIOMD0000000233.png" format="http://purl.org/NET/mediatypes/image/png" master="false"/>
  <content location="BIOMD0000000233.sci" format="http://purl.org/NET/mediatypes/application/x-scilab" master="false"/>
  <content location="BIOMD0000000233.svg" format="http://purl.org/NET/mediatypes/image/svg+xml" master="false"/>
  <content location="BIOMD0000000233.vcml" format="http://purl.org/NET/mediatypes/application/vcml+xml" master="false"/>
  <content location="BIOMD0000000233_url.sedml" format="http://identifiers.org/combine.specifications/sed-ml" master="true"/>
  <content location="BIOMD0000000233_url.xml" format="http://identifiers.org/combine.specifications/sbml" master="false"/>
  <content location="PMC2749052" format="http://purl.org/NET/mediatypes/application/octet-stream" master="false"/>
  <content location="PMC2749052/1752-0509-3-90-1.gif" format="http://purl.org/NET/mediatypes/image/gif" master="false"/>
  <content location="PMC2749052/1752-0509-3-90-1.jpg" format="http://purl.org/NET/mediatypes/image/jpeg" master="false"/>
  <content location="PMC2749052/1752-0509-3-90-2.gif" format="http://purl.org/NET/mediatypes/image/gif" master="false"/>
  <content location="PMC2749052/1752-0509-3-90-2.jpg" format="http://purl.org/NET/mediatypes/image/jpeg" master="false"/>
  <content location="PMC2749052/1752-0509-3-90-3.gif" format="http://purl.org/NET/mediatypes/image/gif" master="false"/>
  <content location="PMC2749052/1752-0509-3-90-3.jpg" format="http://purl.org/NET/mediatypes/image/jpeg" master="false"/>
  <content location="PMC2749052/1752-0509-3-90-i1.gif" format="http://purl.org/NET/mediatypes/image/gif" master="false"/>
  <content location="PMC2749052/1752-0509-3-90-i10.gif" format="http://purl.org/NET/mediatypes/image/gif" master="false"/>
  <content location="PMC2749052/1752-0509-3-90-i11.gif" format="http://purl.org/NET/mediatypes/image/gif" master="false"/>
  <content location="PMC2749052/1752-0509-3-90-i12.gif" format="http://purl.org/NET/mediatypes/image/gif" master="false"/>
  <content location="PMC2749052/1752-0509-3-90-i13.gif" format="http://purl.org/NET/mediatypes/image/gif" master="false"/>
  <content location="PMC2749052/1752-0509-3-90-i14.gif" format="http://purl.org/NET/mediatypes/image/gif" master="false"/>
  <content location="PMC2749052/1752-0509-3-90-i15.gif" format="http://purl.org/NET/mediatypes/image/gif" master="false"/>
  <content location="PMC2749052/1752-0509-3-90-i16.gif" format="http://purl.org/NET/mediatypes/image/gif" master="false"/>
  <content location="PMC2749052/1752-0509-3-90-i17.gif" format="http://purl.org/NET/mediatypes/image/gif" master="false"/>
  <content location="PMC2749052/1752-0509-3-90-i18.gif" format="http://purl.org/NET/mediatypes/image/gif" master="false"/>
  <content location="PMC2749052/1752-0509-3-90-i19.gif" format="http://purl.org/NET/mediatypes/image/gif" master="false"/>
  <content location="PMC2749052/1752-0509-3-90-i2.gif" format="http://purl.org/NET/mediatypes/image/gif" master="false"/>
  <content location="PMC2749052/1752-0509-3-90-i20.gif" format="http://purl.org/NET/mediatypes/image/gif" master="false"/>
  <content location="PMC2749052/1752-0509-3-90-i21.gif" format="http://purl.org/NET/mediatypes/image/gif" master="false"/>
  <content location="PMC2749052/1752-0509-3-90-i22.gif" format="http://purl.org/NET/mediatypes/image/gif" master="false"/>
  <content location="PMC2749052/1752-0509-3-90-i23.gif" format="http://purl.org/NET/mediatypes/image/gif" master="false"/>
  <content location="PMC2749052/1752-0509-3-90-i24.gif" format="http://purl.org/NET/mediatypes/image/gif" master="false"/>
  <content location="PMC2749052/1752-0509-3-90-i25.gif" format="http://purl.org/NET/mediatypes/image/gif" master="false"/>
  <content location="PMC2749052/1752-0509-3-90-i26.gif" format="http://purl.org/NET/mediatypes/image/gif" master="false"/>
  <content location="PMC2749052/1752-0509-3-90-i27.gif" format="http://purl.org/NET/mediatypes/image/gif" master="false"/>
  <content location="PMC2749052/1752-0509-3-90-i28.gif" format="http://purl.org/NET/mediatypes/image/gif" master="false"/>
  <content location="PMC2749052/1752-0509-3-90-i29.gif" format="http://purl.org/NET/mediatypes/image/gif" master="false"/>
  <content location="PMC2749052/1752-0509-3-90-i3.gif" format="http://purl.org/NET/mediatypes/image/gif" master="false"/>
  <content location="PMC2749052/1752-0509-3-90-i30.gif" format="http://purl.org/NET/mediatypes/image/gif" master="false"/>
  <content location="PMC2749052/1752-0509-3-90-i31.gif" format="http://purl.org/NET/mediatypes/image/gif" master="false"/>
  <content location="PMC2749052/1752-0509-3-90-i32.gif" format="http://purl.org/NET/mediatypes/image/gif" master="false"/>
  <content location="PMC2749052/1752-0509-3-90-i33.gif" format="http://purl.org/NET/mediatypes/image/gif" master="false"/>
  <content location="PMC2749052/1752-0509-3-90-i34.gif" format="http://purl.org/NET/mediatypes/image/gif" master="false"/>
  <content location="PMC2749052/1752-0509-3-90-i35.gif" format="http://purl.org/NET/mediatypes/image/gif" master="false"/>
  <content location="PMC2749052/1752-0509-3-90-i36.gif" format="http://purl.org/NET/mediatypes/image/gif" master="false"/>
  <content location="PMC2749052/1752-0509-3-90-i37.gif" format="http://purl.org/NET/mediatypes/image/gif" master="false"/>
  <content location="PMC2749052/1752-0509-3-90-i38.gif" format="http://purl.org/NET/mediatypes/image/gif" master="false"/>
  <content location="PMC2749052/1752-0509-3-90-i39.gif" format="http://purl.org/NET/mediatypes/image/gif" master="false"/>
  <content location="PMC2749052/1752-0509-3-90-i4.gif" format="http://purl.org/NET/mediatypes/image/gif" master="false"/>
  <content location="PMC2749052/1752-0509-3-90-i40.gif" format="http://purl.org/NET/mediatypes/image/gif" master="false"/>
  <content location="PMC2749052/1752-0509-3-90-i41.gif" format="http://purl.org/NET/mediatypes/image/gif" master="false"/>
  <content location="PMC2749052/1752-0509-3-90-i42.gif" format="http://purl.org/NET/mediatypes/image/gif" master="false"/>
  <content location="PMC2749052/1752-0509-3-90-i43.gif" format="http://purl.org/NET/mediatypes/image/gif" master="false"/>
  <content location="PMC2749052/1752-0509-3-90-i44.gif" format="http://purl.org/NET/mediatypes/image/gif" master="false"/>
  <content location="PMC2749052/1752-0509-3-90-i45.gif" format="http://purl.org/NET/mediatypes/image/gif" master="false"/>
  <content location="PMC2749052/1752-0509-3-90-i46.gif" format="http://purl.org/NET/mediatypes/image/gif" master="false"/>
  <content location="PMC2749052/1752-0509-3-90-i47.gif" format="http://purl.org/NET/mediatypes/image/gif" master="false"/>
  <content location="PMC2749052/1752-0509-3-90-i48.gif" format="http://purl.org/NET/mediatypes/image/gif" master="false"/>
  <content location="PMC2749052/1752-0509-3-90-i5.gif" format="http://purl.org/NET/mediatypes/image/gif" master="false"/>
  <content location="PMC2749052/1752-0509-3-90-i6.gif" format="http://purl.org/NET/mediatypes/image/gif" master="false"/>
  <content location="PMC2749052/1752-0509-3-90-i7.gif" format="http://purl.org/NET/mediatypes/image/gif" master="false"/>
  <content location="PMC2749052/1752-0509-3-90-i8.gif" format="http://purl.org/NET/mediatypes/image/gif" master="false"/>
  <content location="PMC2749052/1752-0509-3-90-i9.gif" format="http://purl.org/NET/mediatypes/image/gif" master="false"/>
  <content location="PMC2749052/1752-0509-3-90.nxml" format="http://purl.org/NET/mediatypes/application/octet-stream" master="false"/>
  <content location="PMC2749052/1752-0509-3-90.pdf" format="http://purl.org/NET/mediatypes/application/PDF" master="false"/>
  <content location="curation_image.png" format="http://purl.org/NET/mediatypes/image/png" master="false"/>
  <content location="curation_notes.txt" format="http://purl.org/NET/mediatypes/text/plain" master="false"/>
  <content location="metadata.rdf" format="http://purl.org/NET/mediatypes/application/rdf+xml" master="false"/>
</omexManifest>
